FastSAM/__init__.py
FastSAM/model.py
FastSAM/predict.py
FastSAM/prompt.py
FastSAM/utils.py
segment_anything/__init__.py
segment_anything/automatic_mask_generator.py
segment_anything/build_sam.py
segment_anything/predictor.py
segment_anything/modeling/__init__.py
segment_anything/modeling/common.py
segment_anything/modeling/image_encoder.py
segment_anything/modeling/mask_decoder.py
segment_anything/modeling/prompt_encoder.py
segment_anything/modeling/sam.py
segment_anything/modeling/transformer.py
segment_anything/utils/__init__.py
segment_anything/utils/amg.py
segment_anything/utils/onnx.py
segment_anything/utils/transforms.py
NP_SAM-0.1.dist-info/LICENSE.txt
NP_SAM-0.1.dist-info/METADATA
NP_SAM-0.1.dist-info/WHEEL
NP_SAM-0.1.dist-info/top_level.txt
NP_SAM-0.1.dist-info/RECORD
