Metadata-Version: 2.1
Name: NP-SAM
Version: 0.1
Summary: NP-SAM is an easy-to-use segmentation and analysis tool for nanoparticles and more.
Home-page: https://gitlab.au.dk/disorder/np-sam
Author: Torben Villadsen & Rasmus Larsen
Author-email: torben-v@hotmail.com
License: Apache License
Classifier: Programming Language :: Python :: 3
Classifier: License :: OSI Approved :: MIT License
Requires-Python: >=3.10
License-File: LICENSE.txt
Requires-Dist: numba (==0.57.0)
Requires-Dist: numpy (==1.24.3)
Requires-Dist: opencv-python (==4.8.0.74)
Requires-Dist: pandas (==2.0.1)
Requires-Dist: matplotlib (==3.7.1)
Requires-Dist: scikit-image (==0.20.0)
Requires-Dist: ipympl (==0.9.3)
Requires-Dist: PyQt5 (==5.15.9)
Requires-Dist: Pillow (>=7.1.2)
Requires-Dist: ultralytics (==8.0.120)
Requires-Dist: jupyterlab (==4.0.7)
